{
	"clean": [
		"tmp/",
		"wp-content/themes/bars2013/"
	],
	"dest": {
		"php": "wp-content/themes/bars2013/",
		"lib": "wp-content/themes/bars2013/js/",
		"css": "wp-content/themes/bars2013/css/",
		"img": "wp-content/themes/bars2013/images/",
		"misc": "wp-content/themes/bars2013/resources/",
		"sprites": "wp-content/themes/bars2013/images/sprites.png",
		"cssSpritesImgPath": "images/sprites.png",
		"libOutput": "wp-content/themes/bars2013/js/lib.min.js",
		"cssOutput": "wp-content/themes/bars2013/style.css"
	},

	"tmp": "tmp/",

	"src": {
		"lib": [
			"lib/fancybox/source/jquery.fancybox.js",
			"lib/jquery-form/jquery.form.js",
			"lib/jquery-validation/dist/jquery.validate.js",
			"lib/jQuery.dotdotdot/src/js/jquery.dotdotdot.js",
			"lib/imgLiquid/js/imgLiquid.js",
			"lib/jquery-focuspoint/js/jquery.focuspoint.js"
		],

		"css": [
			"css/imports.css",
			"css/links.css",
			"css/text.css",
			"css/sponsors.css",
			"css/contact.css",
			"css/main.css",
			"css/genericons/genericons.css",
			"css/slider.css",
			"css/sprites.css",
			"lib/jquery-focuspoint/css/focuspoint.css"
		],

		"js": [
			"js/bars.js",
			"js/contact.js",
			"js/slider.js"
		],

		"img": [
			"img/bars2013/*",
			"img/bars2014/*",
			"img/logo_bg.png",
			"img/auspiciantes.png",
			"img/bgpattern2.png",
			"img/bgpattern3.png",
			"img/bottom_footer_back.png",
			"img/screenshot.png",
			"img/scratch.png",
			"img/scratchs_2.png"
		],

		"sprites": [
			"img/convocatoria2014.png",
			"img/hover_convocatoria2014.png",
			"img/hover_facebook.png",
			"img/facebook.png",
			"img/hover_flickr.png",
			"img/flickr.png",
			"img/hover_twitter.png",
			"img/twitter.png",
			"img/hover_tumblr.png",
			"img/tumblr.png",
			"img/hover_youtube.png",
			"img/youtube.png",
			"img/hover_festeringslime.png",
			"img/festeringslime.png",
			"img/footer_logo.png",
			"img/header.png",
			"img/loguito.png",
			"img/arrows.png"
		],

		"php": [
			"php/*",
			"!php/exportmovies.php"
		],

		"misc": [
			"misc/**/*"
		]
	},

	"fancybox": {
		"src" : [
			"lib/fancybox/source/jquery.fancybox.css",
			"lib/fancybox/source/blank.gif",
			"lib/fancybox/source/fancybox_loading.gif",
			"lib/fancybox/source/fancybox_loading@2x.gif",
			"lib/fancybox/source/fancybox_overlay.png",
			"lib/fancybox/source/fancybox_sprite.png",
			"lib/fancybox/source/fancybox_sprite@2x.png"
		],
		"dest" : "wp-content/themes/bars2013/fancybox/"
	},

	"vendor": {
		"src" : "vendor/**/*",
		"dest" : "wp-content/themes/bars2013/"
	}
}